{"dependencies":[{"name":"../core/core.js","loc":{"line":1,"column":21}}],"generated":{"js":"var Crafty = require('../core/core.js');\n\n\nCrafty.extend({\n    /**@\n     * #Crafty.diamondIso\n     * @category 2D\n     * @kind CoreObject\n     * \n     * Place entities in a 45deg diamond isometric fashion. It is similar to isometric but has another grid locations\n     * In this mode, the x axis and y axis are aligned to the edges of tiles with x increasing being down and to the\n     * right and y being down and to the left.\n     */\n    diamondIso: {\n        _tile: {\n            width: 0,\n            height: 0\n        },\n        getTileDimensions: function(){\n            return {w:this._tile.width,h:this._tile.height};\n        },\n        _map: {\n            width: 0,\n            height: 0\n        },\n        _origin: {\n            x: 0,\n            y: 0\n        },\n        _tiles: [],\n        getTile: function(x,y,z){\n            return this._tiles[x][y][z];\n        },\n        /**@\n         * #Crafty.diamondIso.init\n         * @comp Crafty.diamondIso\n         * @kind Method\n         * \n         * @sign public this Crafty.diamondIso.init(Number tileWidth,Number tileHeight,Number mapWidth,Number mapHeight)\n         * @param tileWidth - The size of base tile width's grid space in Pixel\n         * @param tileHeight - The size of base tile height grid space in Pixel\n         * @param mapWidth - The width of whole map in Tiles\n         * @param mapHeight - The height of whole map in Tiles\n         * @param x - the x coordinate of the TOP corner of the 0,0 tile\n         * @param y - the y coordinate of the TOP corner of the 0,0, tile\n         *\n         * Method used to initialize the size of the isometric placement.\n         * Recommended to use a size alues in the power of `2` (128, 64 or 32).\n         * This makes it easy to calculate positions and implement zooming.\n         *\n         * @example\n         * ~~~\n         * var iso = Crafty.diamondIso.init(64,128,20,20);\n         * ~~~\n         *\n         * @see Crafty.diamondIso.place\n         */\n        init: function (tw, th, mw, mh, x, y) {\n            this._tile.width = parseInt(tw, 10);\n            this._tile.height = parseInt(th, 10) || parseInt(tw, 10) / 2;\n            this._tile.r = this._tile.width / this._tile.height;\n\n            this._map.width = parseInt(mw, 10);\n            this._map.height = parseInt(mh, 10) || parseInt(mw, 10);\n            for (var i=0; i<mw; i++) {\n                this._tiles[i]=Array();\n                for (var j=0; j<mh; j++){\n                this._tiles[i][j]=Array();\n                }\n            }\n            this.x = parseInt(x,10) || 0;\n            this.y = parseInt(y,10) || 0;\n            this.layerZLevel= (mw+mh+1);\n            return this;\n        },\n        /**@\n         * #Crafty.diamondIso.place\n         * @comp Crafty.diamondIso\n         * @kind Method\n         * \n         * @sign public this Crafty.diamondIso.place(Entity tile,Number x, Number y, Number layer)\n         * @param x - The `x` position to place the tile\n         * @param y - The `y` position to place the tile\n         * @param layer - The `z` position to place the tile\n         * @param tile - The entity that should be position in the isometric fashion\n         *\n         * Use this method to place an entity in an isometric grid.\n         *\n         * @example\n         * ~~~\n         * var iso = Crafty.diamondIso.init(64,128,20,20);\n         * isos.place(Crafty.e('2D, DOM, Color').color('red').attr({w:128, h:128}),1,1,2);\n         * ~~~\n         *\n         * @see Crafty.diamondIso.size\n         */\n        place: function (obj, x, y, layer) {\n            var pos = this.pos2px(x, y);\n            //this calculation is weird because tile sprites are h*2\n            //for tiles of size h in isometric\n            var spriteHeight =obj.h/this._tile.height;\n            obj.x = pos.x;\n            obj.y = pos.y - (spriteHeight-2)*this._tile.height - this._tile.height*layer;\n            obj.z = this.getZAtLoc(x,y,layer);\n            for (var i=0; i<=spriteHeight-2; i++) {\n                var prevTile = this._tiles[x][y][layer+i];\n                if (prevTile && prevTile !== obj){\n                    prevTile.destroy();\n                }\n                this._tiles[x][y][layer+i] = obj;\n            }\n            return this;\n\n        },\n        detachTile: function(obj){\n            for (var _x=0; _x<this._map.width; _x++){\n                for (var _y=0; _y<this._map.height; _y++){\n                    var len = this._tiles[_x][_y].length;\n                    for(var _z=0; _z<len; _z++){\n                        if (this._tiles[_x][_y][_z] && obj === this._tiles[_x][_y][_z]){\n                            var tHeight=obj.h/this._tile.height;\n                            for (var i=0; i<tHeight; i++){\n                                this._tiles[_x][_y][_z+i] = undefined;\n                            }\n                            return {\n                                x:_x,\n                                y:_y,\n                                z:_z\n                            };\n                        }\n\n                    }\n                }\n            }\n            return false;\n        },\n        centerAt: function (x, y) {\n            var pos = this.pos2px(x, y);\n            Crafty.viewport.x = -pos.x + Crafty.viewport.width / 2 - this._tile.width;\n            Crafty.viewport.y = -pos.y + Crafty.viewport.height / 2;\n\n        },\n        getZAtLoc: function(x,y,layer){\n            return this.layerZLevel * layer + x+y;\n        },\n        pos2px: function (x, y) {\n        /* This returns the correct coordinates to place the \n        object's top and left to fit inside the grid, which is\n        NOT inside of the tile for an isometric grid.  IF you\n        want the top corner of the diamond add tile width/2 */\n            return {\n                x: this.x + ((x - y - 1) * this._tile.width / 2),\n                y: this.y + ((x + y) * this._tile.height / 2)\n            };\n        },\n        px2pos: function (left, top) {\n        /* This returns the x/y coordinates on z level 0.\n        @TODO add a specifying z level\n        */\n            var v1 = (top - this.y)/this._tile.height;\n            var v2 = (left - this.x)/this._tile.width;\n            var x = v1+v2;\n            var y = v1-v2;\n            var inX = x>0 && x<this._map.width;\n            var inY = y>0 && y<this._map.height;\n            if (!inX || !inY){\n                return undefined;\n            }\n            return {\n                x: ~~x,\n                y: ~~y\n            };\n        },\n        getOverlappingTiles: function(x,y){\n        /* This will find all of the tiles that might be at a given x/y in pixels */\n                var pos = this.px2pos(x,y);\n                var tiles = [];\n                var _x = ~~pos.x;\n                var _y = ~~pos.y;\n                var maxX = this._map.width - _x;\n                var maxY = this._map.height - _y;\n                var furthest = Math.min(maxX, maxY);\n                var obj = this._tiles[_x][_y][1];\n                if (obj){\n                    tiles.push(obj);\n                }\n                for (var i=1; i<furthest; i++){\n                    var _obj= this._tiles[_x+i][_y+i][i];\n                    if (_obj){\n                        tiles.push(_obj);\n                    }\n                }\n                return tiles;\n        },\n        polygon: function (obj) {\n            /*I don't know what this is trying to do...*/\n            obj.requires(\"Collision\");\n            var marginX = 0,\n                marginY = 0;\n            var points = [\n                marginX - 0, obj.h - marginY - this._tile.height / 2,\n                marginX - this._tile.width / 2, obj.h - marginY - 0,\n                marginX - this._tile.width, obj.h - marginY - this._tile.height / 2,\n                marginX - this._tile.width / 2, obj.h - marginY - this._tile.height\n            ];\n            var poly = new Crafty.polygon(points);\n            return poly;\n\n        }\n    }\n\n});\n"},"hash":"2bfc654c047d197c743edab79a59318f"}